pykrotik/__init__.py
pykrotik-0.1.0.dist-info/METADATA
pykrotik-0.1.0.dist-info/WHEEL
pykrotik-0.1.0.dist-info/top_level.txt
pykrotik-0.1.0.dist-info/RECORD
