Metadata-Version: 2.1
Name: pykrotik
Version: 0.1.0
Requires-Dist: pydantic
Provides-Extra: dev
Requires-Dist: black ; extra == 'dev'
Requires-Dist: build ; extra == 'dev'
Requires-Dist: pytest ; extra == 'dev'
Requires-Dist: pytest-asyncio ; extra == 'dev'
Requires-Dist: twine ; extra == 'dev'
